doddq/__init__.py
doddq/helpers.py
doddq/rodeo.py
doddq-1.5.dist-info/LICENSE.md
doddq-1.5.dist-info/METADATA
doddq-1.5.dist-info/WHEEL
doddq-1.5.dist-info/top_level.txt
doddq-1.5.dist-info/RECORD
