Metadata-Version: 2.1
Name: doddq
Version: 1.5
Summary: A simple library for use with Qiskit.
Home-page: https://github.com/tomdodd4598/doddq
Author: Tom Dodd
Author-email: joedodd35@gmail.com
Project-URL: Issues, https://github.com/tomdodd4598/doddq/issues
Classifier: Programming Language :: Python :: 3
Classifier: License :: OSI Approved :: MIT License
Classifier: Operating System :: OS Independent
Requires-Python: >=3.9
License-File: LICENSE.md
Requires-Dist: numba
Requires-Dist: numpy
Requires-Dist: qiskit
